zero_llm/__init__.py
zero_llm-0.0.1.dist-info/licenses/LICENSE
zero_llm-0.0.1.dist-info/METADATA
zero_llm-0.0.1.dist-info/WHEEL
zero_llm-0.0.1.dist-info/top_level.txt
zero_llm-0.0.1.dist-info/RECORD
