Metadata-Version: 2.4
Name: zero-llm
Version: 0.0.1
Summary: A test package for checking PyPI name availability
Home-page: https://github.com/test/test-package
Author: Test Author
Author-email: zero-llm <test@example.com>
License: MIT
Project-URL: Homepage, https://github.com/test/test-package
Classifier: Programming Language :: Python :: 3
Classifier: License :: OSI Approved :: MIT License
Classifier: Operating System :: OS Independent
Requires-Python: >=3.6
License-File: LICENSE
Dynamic: author
Dynamic: home-page
Dynamic: license-file
Dynamic: requires-python
